Workbook

Sheet Hypotheses
A1: MoriWords — Hypothèses du prévisionnel
A2: Légende : texte BLEU sur fond jaune = cellule à modifier. Tout le reste se recalcule tout seul.
A4: Prix & paiement
A5: Prix de l'abonnement mensuel (TTC = HT si franchise TVA) | B5: 4.99 | C5: Recommandation : 4,99 €/mois
A6: Stripe — commission en % | B6: 0.015 | C6: Tarif Stripe cartes UE standard (vérifier sur stripe.com/fr/pricing)
A7: Stripe — frais fixe par paiement | B7: 0.25 | C7: Tarif Stripe cartes UE standard
A8: Cotisations sociales micro-entreprise (% du CA) | B8: 0.23 | C8: Hypothèse ~22-25 % selon BIC/BNC ; à vérifier sur autoentrepreneur.urssaf.fr (ACRE = moitié la 1re année)
A9: Croissance
A10: Nouveaux inscrits le 1er mois | B10: 50 | C10: Hypothèse : lancement discret (réseaux, Reddit, Discord japonais)
A11: Croissance mensuelle des nouveaux inscrits | B11: 0.15 | C11: Hypothèse
A12: Taux de conversion inscrit → payant | B12: 0.05 | C12: Hypothèse : 2-5 % est courant pour un freemium
A13: Désabonnement mensuel (churn) des payants | B13: 0.08 | C13: Hypothèse
A14: Part des gratuits encore actifs chaque mois | B14: 0.3 | C14: Hypothèse : beaucoup d'inscrits testent puis décrochent
A15: Claude (modèle Haiku 4.5)
A16: Prix entrée ($ / million de tokens) | B16: 1 | C16: Tarif Anthropic Haiku 4.5
A17: Prix sortie ($ / million de tokens) | B17: 5 | C17: Tarif Anthropic Haiku 4.5
A18: Taux de change (1 $ = x €) | B18: 0.9 | C18: À ajuster au cours du jour
A19: Économie grâce aux caches partagés (sur actions « en cache ») | B19: 0.3 | C19: Hypothèse : grandit avec le nombre d'utilisateurs (un mot traduit une fois sert à tous)
A20: Frais fixes mensuels
A21: Vercel Pro | B21: 18 | C21: 20 $/mois — le plan Hobby gratuit interdit l'usage commercial
A22: Base PostgreSQL (Neon / Supabase) | B22: 18 | C22: ~19-25 $/mois pour un plan payant
A23: Nom de domaine | B23: 1.5 | C23: ~15-20 €/an
A24: Divers (emails transactionnels, compta, outils) | B24: 5 | C24: Hypothèse
A25: Total frais fixes / mois | B25: =SUM($B$21,$B$22,$B$23,$B$24)
A27: Coût par action Claude (estimé depuis les prompts du code)
A28: Action | B28: Tokens entrée | C28: Tokens sortie | D28: Coût / appel (€) | E28: En cache ? | F28: Appels / mois — payant | G28: Appels / mois — gratuit (quota)
A29: Traduction mot / phrase | B29: 150 | C29: 120 | D29: =(B29*$B$16+C29*$B$17)/1000000*$B$18 | E29: oui | F29: 300 | G29: 20
A30: 5 exemples pour une carte | B30: 300 | C30: 600 | D30: =(B30*$B$16+C30*$B$17)/1000000*$B$18 | E30: oui | F30: 100 | G30: 5
A31: Correction d'exercice | B31: 450 | C31: 400 | D31: =(B31*$B$16+C31*$B$17)/1000000*$B$18 | E31: non | F31: 100 | G31: 5
A32: Texte généré (citation, dialogue, news…) | B32: 450 | C32: 300 | D32: =(B32*$B$16+C32*$B$17)/1000000*$B$18 | E32: non | F32: 30 | G32: 3
A33: Exercices de grammaire (10 par point) | B33: 300 | C33: 1000 | D33: =(B33*$B$16+C33*$B$17)/1000000*$B$18 | E33: oui | F33: 2 | G33: 0
A35: Coût Claude par abonné payant / mois | B35: =SUMPRODUCT(D29:D33,F29:F33,1-(E29:E33="oui")*$B$19) | C35: Profil « régulier », après économie de cache
A36: Coût Claude par gratuit actif / mois | B36: =SUMPRODUCT(D29:D33,G29:G33,1-(E29:E33="oui")*$B$19) | C36: Avec quota sur l'offre gratuite
A37: Rentabilité par abonné
A38: Reste après Stripe + URSSAF | B38: =$B$5-($B$5*$B$6+$B$7)-$B$5*$B$8
A39: Marge par abonné (après Claude) | B39: =$B$38-$B$35
A40: Seuil de rentabilité (abonnés payants) | B40: =IF($B$39>0,ROUNDUP($B$25/$B$39,0),"jamais") | C40: Sans compter le coût des gratuits (voir onglet Prévisionnel)

Sheet Previsionnel 24 mois
A1: MoriWords — Prévisionnel sur 24 mois
A2: Tout est calculé à partir de l'onglet Hypotheses (liens en vert). Ne rien saisir ici.
A4: Mois | B4: Nouveaux inscrits | C4: Inscrits cumulés | D4: Abonnés payants | E4: Gratuits actifs | F4: Chiffre d'affaires | G4: Frais Stripe | H4: Cotisations URSSAF | I4: Coût Claude — payants | J4: Coût Claude — gratuits | K4: Frais fixes | L4: Résultat du mois | M4: Résultat cumulé | N4: (aide) mois rentable | O4: (aide) cumul positif
A5: M1 | B5: =Hypotheses!$B$10 | C5: =B5 | D5: =B5*Hypotheses!$B$12 | E5: =MAX(0,(C5-D5)*Hypotheses!$B$14) | F5: =D5*Hypotheses!$B$5 | G5: =D5*(Hypotheses!$B$5*Hypotheses!$B$6+Hypotheses!$B$7) | H5: =F5*Hypotheses!$B$8 | I5: =D5*Hypotheses!$B$35 | J5: =E5*Hypotheses!$B$36 | K5: =Hypotheses!$B$25 | L5: =F5-G5-H5-I5-J5-K5 | M5: =L5 | N5: =IF(L5>0,1,99) | O5: =IF(M5>0,1,99)
A6: M2 | B6: =B5*(1+Hypotheses!$B$11) | C6: =C5+B6 | D6: =D5*(1-Hypotheses!$B$13)+B6*Hypotheses!$B$12 | E6: =MAX(0,(C6-D6)*Hypotheses!$B$14) | F6: =D6*Hypotheses!$B$5 | G6: =D6*(Hypotheses!$B$5*Hypotheses!$B$6+Hypotheses!$B$7) | H6: =F6*Hypotheses!$B$8 | I6: =D6*Hypotheses!$B$35 | J6: =E6*Hypotheses!$B$36 | K6: =Hypotheses!$B$25 | L6: =F6-G6-H6-I6-J6-K6 | M6: =M5+L6 | N6: =IF(L6>0,2,99) | O6: =IF(M6>0,2,99)
A7: M3 | B7: =B6*(1+Hypotheses!$B$11) | C7: =C6+B7 | D7: =D6*(1-Hypotheses!$B$13)+B7*Hypotheses!$B$12 | E7: =MAX(0,(C7-D7)*Hypotheses!$B$14) | F7: =D7*Hypotheses!$B$5 | G7: =D7*(Hypotheses!$B$5*Hypotheses!$B$6+Hypotheses!$B$7) | H7: =F7*Hypotheses!$B$8 | I7: =D7*Hypotheses!$B$35 | J7: =E7*Hypotheses!$B$36 | K7: =Hypotheses!$B$25 | L7: =F7-G7-H7-I7-J7-K7 | M7: =M6+L7 | N7: =IF(L7>0,3,99) | O7: =IF(M7>0,3,99)
A8: M4 | B8: =B7*(1+Hypotheses!$B$11) | C8: =C7+B8 | D8: =D7*(1-Hypotheses!$B$13)+B8*Hypotheses!$B$12 | E8: =MAX(0,(C8-D8)*Hypotheses!$B$14) | F8: =D8*Hypotheses!$B$5 | G8: =D8*(Hypotheses!$B$5*Hypotheses!$B$6+Hypotheses!$B$7) | H8: =F8*Hypotheses!$B$8 | I8: =D8*Hypotheses!$B$35 | J8: =E8*Hypotheses!$B$36 | K8: =Hypotheses!$B$25 | L8: =F8-G8-H8-I8-J8-K8 | M8: =M7+L8 | N8: =IF(L8>0,4,99) | O8: =IF(M8>0,4,99)
A9: M5 | B9: =B8*(1+Hypotheses!$B$11) | C9: =C8+B9 | D9: =D8*(1-Hypotheses!$B$13)+B9*Hypotheses!$B$12 | E9: =MAX(0,(C9-D9)*Hypotheses!$B$14) | F9: =D9*Hypotheses!$B$5 | G9: =D9*(Hypotheses!$B$5*Hypotheses!$B$6+Hypotheses!$B$7) | H9: =F9*Hypotheses!$B$8 | I9: =D9*Hypotheses!$B$35 | J9: =E9*Hypotheses!$B$36 | K9: =Hypotheses!$B$25 | L9: =F9-G9-H9-I9-J9-K9 | M9: =M8+L9 | N9: =IF(L9>0,5,99) | O9: =IF(M9>0,5,99)
A10: M6 | B10: =B9*(1+Hypotheses!$B$11) | C10: =C9+B10 | D10: =D9*(1-Hypotheses!$B$13)+B10*Hypotheses!$B$12 | E10: =MAX(0,(C10-D10)*Hypotheses!$B$14) | F10: =D10*Hypotheses!$B$5 | G10: =D10*(Hypotheses!$B$5*Hypotheses!$B$6+Hypotheses!$B$7) | H10: =F10*Hypotheses!$B$8 | I10: =D10*Hypotheses!$B$35 | J10: =E10*Hypotheses!$B$36 | K10: =Hypotheses!$B$25 | L10: =F10-G10-H10-I10-J10-K10 | M10: =M9+L10 | N10: =IF(L10>0,6,99) | O10: =IF(M10>0,6,99)
A11: M7 | B11: =B10*(1+Hypotheses!$B$11) | C11: =C10+B11 | D11: =D10*(1-Hypotheses!$B$13)+B11*Hypotheses!$B$12 | E11: =MAX(0,(C11-D11)*Hypotheses!$B$14) | F11: =D11*Hypotheses!$B$5 | G11: =D11*(Hypotheses!$B$5*Hypotheses!$B$6+Hypotheses!$B$7) | H11: =F11*Hypotheses!$B$8 | I11: =D11*Hypotheses!$B$35 | J11: =E11*Hypotheses!$B$36 | K11: =Hypotheses!$B$25 | L11: =F11-G11-H11-I11-J11-K11 | M11: =M10+L11 | N11: =IF(L11>0,7,99) | O11: =IF(M11>0,7,99)
A12: M8 | B12: =B11*(1+Hypotheses!$B$11) | C12: =C11+B12 | D12: =D11*(1-Hypotheses!$B$13)+B12*Hypotheses!$B$12 | E12: =MAX(0,(C12-D12)*Hypotheses!$B$14) | F12: =D12*Hypotheses!$B$5 | G12: =D12*(Hypotheses!$B$5*Hypotheses!$B$6+Hypotheses!$B$7) | H12: =F12*Hypotheses!$B$8 | I12: =D12*Hypotheses!$B$35 | J12: =E12*Hypotheses!$B$36 | K12: =Hypotheses!$B$25 | L12: =F12-G12-H12-I12-J12-K12 | M12: =M11+L12 | N12: =IF(L12>0,8,99) | O12: =IF(M12>0,8,99)
A13: M9 | B13: =B12*(1+Hypotheses!$B$11) | C13: =C12+B13 | D13: =D12*(1-Hypotheses!$B$13)+B13*Hypotheses!$B$12 | E13: =MAX(0,(C13-D13)*Hypotheses!$B$14) | F13: =D13*Hypotheses!$B$5 | G13: =D13*(Hypotheses!$B$5*Hypotheses!$B$6+Hypotheses!$B$7) | H13: =F13*Hypotheses!$B$8 | I13: =D13*Hypotheses!$B$35 | J13: =E13*Hypotheses!$B$36 | K13: =Hypotheses!$B$25 | L13: =F13-G13-H13-I13-J13-K13 | M13: =M12+L13 | N13: =IF(L13>0,9,99) | O13: =IF(M13>0,9,99)
A14: M10 | B14: =B13*(1+Hypotheses!$B$11) | C14: =C13+B14 | D14: =D13*(1-Hypotheses!$B$13)+B14*Hypotheses!$B$12 | E14: =MAX(0,(C14-D14)*Hypotheses!$B$14) | F14: =D14*Hypotheses!$B$5 | G14: =D14*(Hypotheses!$B$5*Hypotheses!$B$6+Hypotheses!$B$7) | H14: =F14*Hypotheses!$B$8 | I14: =D14*Hypotheses!$B$35 | J14: =E14*Hypotheses!$B$36 | K14: =Hypotheses!$B$25 | L14: =F14-G14-H14-I14-J14-K14 | M14: =M13+L14 | N14: =IF(L14>0,10,99) | O14: =IF(M14>0,10,99)
A15: M11 | B15: =B14*(1+Hypotheses!$B$11) | C15: =C14+B15 | D15: =D14*(1-Hypotheses!$B$13)+B15*Hypotheses!$B$12 | E15: =MAX(0,(C15-D15)*Hypotheses!$B$14) | F15: =D15*Hypotheses!$B$5 | G15: =D15*(Hypotheses!$B$5*Hypotheses!$B$6+Hypotheses!$B$7) | H15: =F15*Hypotheses!$B$8 | I15: =D15*Hypotheses!$B$35 | J15: =E15*Hypotheses!$B$36 | K15: =Hypotheses!$B$25 | L15: =F15-G15-H15-I15-J15-K15 | M15: =M14+L15 | N15: =IF(L15>0,11,99) | O15: =IF(M15>0,11,99)
A16: M12 | B16: =B15*(1+Hypotheses!$B$11) | C16: =C15+B16 | D16: =D15*(1-Hypotheses!$B$13)+B16*Hypotheses!$B$12 | E16: =MAX(0,(C16-D16)*Hypotheses!$B$14) | F16: =D16*Hypotheses!$B$5 | G16: =D16*(Hypotheses!$B$5*Hypotheses!$B$6+Hypotheses!$B$7) | H16: =F16*Hypotheses!$B$8 | I16: =D16*Hypotheses!$B$35 | J16: =E16*Hypotheses!$B$36 | K16: =Hypotheses!$B$25 | L16: =F16-G16-H16-I16-J16-K16 | M16: =M15+L16 | N16: =IF(L16>0,12,99) | O16: =IF(M16>0,12,99)
A17: M13 | B17: =B16*(1+Hypotheses!$B$11) | C17: =C16+B17 | D17: =D16*(1-Hypotheses!$B$13)+B17*Hypotheses!$B$12 | E17: =MAX(0,(C17-D17)*Hypotheses!$B$14) | F17: =D17*Hypotheses!$B$5 | G17: =D17*(Hypotheses!$B$5*Hypotheses!$B$6+Hypotheses!$B$7) | H17: =F17*Hypotheses!$B$8 | I17: =D17*Hypotheses!$B$35 | J17: =E17*Hypotheses!$B$36 | K17: =Hypotheses!$B$25 | L17: =F17-G17-H17-I17-J17-K17 | M17: =M16+L17 | N17: =IF(L17>0,13,99) | O17: =IF(M17>0,13,99)
A18: M14 | B18: =B17*(1+Hypotheses!$B$11) | C18: =C17+B18 | D18: =D17*(1-Hypotheses!$B$13)+B18*Hypotheses!$B$12 | E18: =MAX(0,(C18-D18)*Hypotheses!$B$14) | F18: =D18*Hypotheses!$B$5 | G18: =D18*(Hypotheses!$B$5*Hypotheses!$B$6+Hypotheses!$B$7) | H18: =F18*Hypotheses!$B$8 | I18: =D18*Hypotheses!$B$35 | J18: =E18*Hypotheses!$B$36 | K18: =Hypotheses!$B$25 | L18: =F18-G18-H18-I18-J18-K18 | M18: =M17+L18 | N18: =IF(L18>0,14,99) | O18: =IF(M18>0,14,99)
A19: M15 | B19: =B18*(1+Hypotheses!$B$11) | C19: =C18+B19 | D19: =D18*(1-Hypotheses!$B$13)+B19*Hypotheses!$B$12 | E19: =MAX(0,(C19-D19)*Hypotheses!$B$14) | F19: =D19*Hypotheses!$B$5 | G19: =D19*(Hypotheses!$B$5*Hypotheses!$B$6+Hypotheses!$B$7) | H19: =F19*Hypotheses!$B$8 | I19: =D19*Hypotheses!$B$35 | J19: =E19*Hypotheses!$B$36 | K19: =Hypotheses!$B$25 | L19: =F19-G19-H19-I19-J19-K19 | M19: =M18+L19 | N19: =IF(L19>0,15,99) | O19: =IF(M19>0,15,99)
A20: M16 | B20: =B19*(1+Hypotheses!$B$11) | C20: =C19+B20 | D20: =D19*(1-Hypotheses!$B$13)+B20*Hypotheses!$B$12 | E20: =MAX(0,(C20-D20)*Hypotheses!$B$14) | F20: =D20*Hypotheses!$B$5 | G20: =D20*(Hypotheses!$B$5*Hypotheses!$B$6+Hypotheses!$B$7) | H20: =F20*Hypotheses!$B$8 | I20: =D20*Hypotheses!$B$35 | J20: =E20*Hypotheses!$B$36 | K20: =Hypotheses!$B$25 | L20: =F20-G20-H20-I20-J20-K20 | M20: =M19+L20 | N20: =IF(L20>0,16,99) | O20: =IF(M20>0,16,99)
A21: M17 | B21: =B20*(1+Hypotheses!$B$11) | C21: =C20+B21 | D21: =D20*(1-Hypotheses!$B$13)+B21*Hypotheses!$B$12 | E21: =MAX(0,(C21-D21)*Hypotheses!$B$14) | F21: =D21*Hypotheses!$B$5 | G21: =D21*(Hypotheses!$B$5*Hypotheses!$B$6+Hypotheses!$B$7) | H21: =F21*Hypotheses!$B$8 | I21: =D21*Hypotheses!$B$35 | J21: =E21*Hypotheses!$B$36 | K21: =Hypotheses!$B$25 | L21: =F21-G21-H21-I21-J21-K21 | M21: =M20+L21 | N21: =IF(L21>0,17,99) | O21: =IF(M21>0,17,99)
A22: M18 | B22: =B21*(1+Hypotheses!$B$11) | C22: =C21+B22 | D22: =D21*(1-Hypotheses!$B$13)+B22*Hypotheses!$B$12 | E22: =MAX(0,(C22-D22)*Hypotheses!$B$14) | F22: =D22*Hypotheses!$B$5 | G22: =D22*(Hypotheses!$B$5*Hypotheses!$B$6+Hypotheses!$B$7) | H22: =F22*Hypotheses!$B$8 | I22: =D22*Hypotheses!$B$35 | J22: =E22*Hypotheses!$B$36 | K22: =Hypotheses!$B$25 | L22: =F22-G22-H22-I22-J22-K22 | M22: =M21+L22 | N22: =IF(L22>0,18,99) | O22: =IF(M22>0,18,99)
A23: M19 | B23: =B22*(1+Hypotheses!$B$11) | C23: =C22+B23 | D23: =D22*(1-Hypotheses!$B$13)+B23*Hypotheses!$B$12 | E23: =MAX(0,(C23-D23)*Hypotheses!$B$14) | F23: =D23*Hypotheses!$B$5 | G23: =D23*(Hypotheses!$B$5*Hypotheses!$B$6+Hypotheses!$B$7) | H23: =F23*Hypotheses!$B$8 | I23: =D23*Hypotheses!$B$35 | J23: =E23*Hypotheses!$B$36 | K23: =Hypotheses!$B$25 | L23: =F23-G23-H23-I23-J23-K23 | M23: =M22+L23 | N23: =IF(L23>0,19,99) | O23: =IF(M23>0,19,99)
A24: M20 | B24: =B23*(1+Hypotheses!$B$11) | C24: =C23+B24 | D24: =D23*(1-Hypotheses!$B$13)+B24*Hypotheses!$B$12 | E24: =MAX(0,(C24-D24)*Hypotheses!$B$14) | F24: =D24*Hypotheses!$B$5 | G24: =D24*(Hypotheses!$B$5*Hypotheses!$B$6+Hypotheses!$B$7) | H24: =F24*Hypotheses!$B$8 | I24: =D24*Hypotheses!$B$35 | J24: =E24*Hypotheses!$B$36 | K24: =Hypotheses!$B$25 | L24: =F24-G24-H24-I24-J24-K24 | M24: =M23+L24 | N24: =IF(L24>0,20,99) | O24: =IF(M24>0,20,99)
A25: M21 | B25: =B24*(1+Hypotheses!$B$11) | C25: =C24+B25 | D25: =D24*(1-Hypotheses!$B$13)+B25*Hypotheses!$B$12 | E25: =MAX(0,(C25-D25)*Hypotheses!$B$14) | F25: =D25*Hypotheses!$B$5 | G25: =D25*(Hypotheses!$B$5*Hypotheses!$B$6+Hypotheses!$B$7) | H25: =F25*Hypotheses!$B$8 | I25: =D25*Hypotheses!$B$35 | J25: =E25*Hypotheses!$B$36 | K25: =Hypotheses!$B$25 | L25: =F25-G25-H25-I25-J25-K25 | M25: =M24+L25 | N25: =IF(L25>0,21,99) | O25: =IF(M25>0,21,99)
A26: M22 | B26: =B25*(1+Hypotheses!$B$11) | C26: =C25+B26 | D26: =D25*(1-Hypotheses!$B$13)+B26*Hypotheses!$B$12 | E26: =MAX(0,(C26-D26)*Hypotheses!$B$14) | F26: =D26*Hypotheses!$B$5 | G26: =D26*(Hypotheses!$B$5*Hypotheses!$B$6+Hypotheses!$B$7) | H26: =F26*Hypotheses!$B$8 | I26: =D26*Hypotheses!$B$35 | J26: =E26*Hypotheses!$B$36 | K26: =Hypotheses!$B$25 | L26: =F26-G26-H26-I26-J26-K26 | M26: =M25+L26 | N26: =IF(L26>0,22,99) | O26: =IF(M26>0,22,99)
A27: M23 | B27: =B26*(1+Hypotheses!$B$11) | C27: =C26+B27 | D27: =D26*(1-Hypotheses!$B$13)+B27*Hypotheses!$B$12 | E27: =MAX(0,(C27-D27)*Hypotheses!$B$14) | F27: =D27*Hypotheses!$B$5 | G27: =D27*(Hypotheses!$B$5*Hypotheses!$B$6+Hypotheses!$B$7) | H27: =F27*Hypotheses!$B$8 | I27: =D27*Hypotheses!$B$35 | J27: =E27*Hypotheses!$B$36 | K27: =Hypotheses!$B$25 | L27: =F27-G27-H27-I27-J27-K27 | M27: =M26+L27 | N27: =IF(L27>0,23,99) | O27: =IF(M27>0,23,99)
A28: M24 | B28: =B27*(1+Hypotheses!$B$11) | C28: =C27+B28 | D28: =D27*(1-Hypotheses!$B$13)+B28*Hypotheses!$B$12 | E28: =MAX(0,(C28-D28)*Hypotheses!$B$14) | F28: =D28*Hypotheses!$B$5 | G28: =D28*(Hypotheses!$B$5*Hypotheses!$B$6+Hypotheses!$B$7) | H28: =F28*Hypotheses!$B$8 | I28: =D28*Hypotheses!$B$35 | J28: =E28*Hypotheses!$B$36 | K28: =Hypotheses!$B$25 | L28: =F28-G28-H28-I28-J28-K28 | M28: =M27+L28 | N28: =IF(L28>0,24,99) | O28: =IF(M28>0,24,99)
A29: TOTAL 24 mois | D29: =D28 | F29: =SUM(F5:F28) | G29: =SUM(G5:G28) | H29: =SUM(H5:H28) | I29: =SUM(I5:I28) | J29: =SUM(J5:J28) | K29: =SUM(K5:K28) | L29: =SUM(L5:L28)
A31: Premier mois rentable (résultat du mois > 0) : | D31: =IF(MIN(N5:N28)=99,"pas sur 24 mois","M"&MIN(N5:N28))
A32: Part de Claude dans le CA (24 mois) : | D32: =IF(F29>0,(I29+J29)/F29,0)
A33: Abonnés payants au mois 24 : | D33: =D28
A34: Mois où le cumul redevient positif (pertes du début remboursées) : | D34: =IF(MIN(O5:O28)=99,"pas sur 24 mois","M"&MIN(O5:O28))

Sheet Optimisations
A1: MoriWords — Optimisations avant / après mise en ligne
A3: Priorité | B3: Optimisation | C3: Pourquoi | D3: Où dans le code | E3: Effort | F3: Gain / impact
A4: NÉCESSAIRE | B4: Comptes utilisateurs (modèle User + authentification) | C4: Aujourd'hui l'appli est mono-utilisateur : pas de modèle User dans le schéma, tout le monde verrait les mêmes decks et historiques. | D4: prisma/schema.prisma (Deck, Card, SourceText, ExerciseAttempt… à rattacher à un userId) | E4: Élevé | F4: Indispensable pour vendre un abonnement
A5: NÉCESSAIRE | B5: Paiement Stripe (Checkout + webhooks + statut d'abonnement) | C5: Encaisser, gérer les résiliations et bloquer les fonctions premium si l'abonnement expire. | D5: Nouvelle route src/app/api/billing/* + champ subscriptionStatus sur User | E5: Moyen | F5: Indispensable
A6: NÉCESSAIRE | B6: Quotas par utilisateur sur chaque route qui appelle Claude | C6: Sans limite, un seul utilisateur (ou un bot) peut faire exploser la facture Anthropic. | D6: src/app/api/translate, decks/*/examples, grammar/exercises/correct, source-texts/* | E6: Moyen | F6: Protège la marge : coût max par user connu à l'avance
A7: NÉCESSAIRE | B7: Journaliser l'usage Claude (response.usage) par utilisateur et par action | C7: Remplacer les estimations de ce fichier par des chiffres réels et repérer les abus. | D7: src/lib/feeds/claude-json-generator.ts + src/lib/translation/translate.ts (nouvelle table ClaudeUsage) | E7: Faible | F7: Pilotage : vrais coûts par action
A8: NÉCESSAIRE | B8: Plafond de dépense + alertes dans la console Anthropic | C8: Filet de sécurité si un bug ou un abus déclenche des milliers d'appels. | D8: Console Anthropic (réglage, pas de code) | E8: Très faible | F8: Évite la mauvaise surprise
A9: NÉCESSAIRE | B9: Passer sur Vercel Pro | C9: Le plan Hobby gratuit interdit l'usage commercial. | D9: Tableau de bord Vercel | E9: Très faible | F9: Conformité
A10: NÉCESSAIRE | B10: Mentions légales, CGV, politique de confidentialité (RGPD) | C10: Obligatoire dès qu'on vend en ligne et qu'on stocke des comptes (emails). | D10: Pages statiques + bandeau / consentement si analytics | E10: Faible | F10: Conformité légale
A11: NÉCESSAIRE | B11: Vérifier le droit des « citations d'anime » générées | C11: Des répliques d'œuvres protégées affichées dans un produit payant peuvent poser problème. | D11: src/lib/feeds/anime-quote.ts | E11: Faible | F11: Réduit le risque juridique
A12: OPTIONNEL | B12: Textes du jour partagés (1 génération par jour pour tous) | C12: Aujourd'hui chaque clic sur « citation / dialogue / extrait » rappelle Claude. Un texte du jour commun rend ce coût fixe. | D12: src/app/api/source-texts/* + le cron de vercel.json | E12: Faible | F12: Coût textes : de ~0,06 €/user/mois à quelques centimes par jour au total
A13: OPTIONNEL | B13: Pré-remplir les caches avec l'API Batch (-50 %) | C13: Générer à l'avance les exemples des mots JLPT N5-N3 et tous les points de grammaire : les utilisateurs tombent directement dans le cache. | D13: Script dans scripts/ utilisant client.messages.batches | E13: Moyen | F13: ~5 000 mots × 0,0033 $ × 50 % ≈ 8 $ une seule fois, puis exemples quasi gratuits
A14: OPTIONNEL | B14: Sorties structurées (output_config.format) au lieu d'extraire le JSON à la main | C14: Moins de réponses inexploitables = moins d'erreurs affichées et d'appels relancés par l'utilisateur. | D14: src/lib/feeds/claude-json-generator.ts (extractJsonPayload) | E14: Faible | F14: Fiabilité + quelques % d'appels en moins
... A19: À ÉVITER | B19: Passer sur un modèle plus gros par défaut | C19: Haiku 4.5 est le bon choix pour ces tâches simples ; un modèle plus puissant multiplierait le coût (x2 à x10). Éventuellement pour les corrections d'une offre « premium ». | D19: — | E19: — | F19: —
